cc_connector_cli/__init__.py
cc_connector_cli/connector_cli.py
cc_connector_cli/version.py
cc_connector_cli-0.3.dist-info/LICENSE
cc_connector_cli-0.3.dist-info/WHEEL
cc_connector_cli-0.3.dist-info/METADATA
cc_connector_cli-0.3.dist-info/RECORD
